LICENSE
README.rst
setup.py
MySQLX.egg-info/PKG-INFO
MySQLX.egg-info/SOURCES.txt
MySQLX.egg-info/dependency_links.txt
MySQLX.egg-info/not-zip-safe
MySQLX.egg-info/requires.txt
MySQLX.egg-info/top_level.txt
mysqlx/__init__.py
mysqlx/constant.py
mysqlx/db.py
mysqlx/dbx.py
mysqlx/log_support.py
mysqlx/sql_holder.py
mysqlx/sql_id_exec.py
mysqlx/sql_mapper.py
mysqlx/sql_page_exec.py
mysqlx/sql_support.py
mysqlx/support.py