Metadata-Version: 2.1
Name: MySQLX
Version: 2.2.9
Summary: A thread safe sql executor for MySQL like MyBatis with connection pool. It helps you automatically manage database connections and transactions.
Home-page: https://gitee.com/summry/mysqlx
Author: summy
Author-email: xiazhongbiao@126.com
License: UNKNOWN
Keywords: sql,MySQL,MyBatis,python
Platform: UNKNOWN
Requires-Python: >=3.5
License-File: LICENSE
